[{"OrdersHistory":null,"CurrentAccount":null,"FirstName":"seeta","LastName":"shinde","Email":"seeta.shinde@gmail.com","ContactNumber":"9883764521","Id":"101"},{"OrdersHistory":null,"CurrentAccount":null,"FirstName":"Geeta","LastName":"Jadhav","Email":"geeta.jadhav@gmail.com","ContactNumber":"9883466523","Id":"102"},{"OrdersHistory":null,"CurrentAccount":null,"FirstName":"seeta","LastName":"shinde","Email":"seeta.shinde@gmail.com","ContactNumber":"9883764521","Id":"101"},{"OrdersHistory":null,"CurrentAccount":null,"FirstName":"Geeta","LastName":"Jadhav","Email":"geeta.jadhav@gmail.com","ContactNumber":"9883466523","Id":"102"}]